{"blocks":[{"x":600,"y":260,"text":"начало","width":100,"height":30,"type":"Начало / конец","isMenuBlock":false,"fontSize":14,"textHeight":14,"isBold":false,"isItalic":false,"textAlign":"center","labelsPosition":1},{"x":800,"y":360,"text":"ввод size","width":120,"height":40,"type":"Ввод / вывод","isMenuBlock":false,"fontSize":14,"textHeight":14,"isBold":false,"isItalic":false,"textAlign":"center","labelsPosition":1},{"x":800,"y":420,"text":"size > 1","width":100,"height":40,"type":"Условие","isMenuBlock":false,"fontSize":14,"textHeight":14,"isBold":false,"isItalic":false,"textAlign":"center","labelsPosition":1},{"x":860,"y":480,"text":"Массив в данном задании не может быть меньше 2 элементов.","width":440,"height":40,"type":"Ввод / вывод","isMenuBlock":false,"fontSize":14,"textHeight":14,"isBold":false,"isItalic":false,"textAlign":"center","labelsPosition":1},{"x":1170,"y":480,"text":"break;","width":100,"height":40,"type":"Блок","isMenuBlock":false,"fontSize":14,"textHeight":14,"isBold":false,"isItalic":false,"textAlign":"center","labelsPosition":1},{"x":600,"y":320,"text":"true","width":100,"height":40,"type":"Условие","isMenuBlock":false,"fontSize":14,"textHeight":14,"isBold":false,"isItalic":false,"textAlign":"center","labelsPosition":1},{"x":600,"y":650,"text":"ввод arr[i]","width":120,"height":40,"type":"Ввод / вывод","isMenuBlock":false,"fontSize":14,"textHeight":14,"isBold":false,"isItalic":false,"textAlign":"center","labelsPosition":1},{"x":600,"y":590,"text":"i от 0 до size","width":100,"height":40,"type":"Цикл for","isMenuBlock":false,"fontSize":14,"textHeight":14,"isBold":false,"isItalic":false,"textAlign":"center","labelsPosition":1},{"x":600,"y":750,"text":"draw_float_array","width":140,"height":40,"type":"Подпрограмма","isMenuBlock":false,"fontSize":14,"textHeight":14,"isBold":false,"isItalic":false,"textAlign":"center","labelsPosition":1},{"x":600,"y":810,"text":"bool negative = false;\r\nfloat summ = 0;","width":140,"height":40,"type":"Блок","isMenuBlock":false,"fontSize":14,"textHeight":14,"isBold":false,"isItalic":false,"textAlign":"left","labelsPosition":1},{"x":600,"y":940,"text":"!negative && arr[i] < 0","width":180,"height":60,"type":"Условие","isMenuBlock":false,"fontSize":14,"textHeight":14,"isBold":false,"isItalic":false,"textAlign":"center","labelsPosition":2},{"x":480,"y":1000,"text":"negative = true","width":120,"height":40,"type":"Блок","isMenuBlock":false,"fontSize":14,"textHeight":14,"isBold":false,"isItalic":false,"textAlign":"center","labelsPosition":1},{"x":710,"y":1040,"text":"negative","width":100,"height":40,"type":"Условие","isMenuBlock":false,"fontSize":14,"textHeight":14,"isBold":false,"isItalic":false,"textAlign":"center","labelsPosition":1},{"x":600,"y":870,"text":"i от 0 до size","width":100,"height":40,"type":"Цикл for","isMenuBlock":false,"fontSize":14,"textHeight":14,"isBold":false,"isItalic":false,"textAlign":"center","labelsPosition":1},{"x":800,"y":1090,"text":"summ += fabs(arr[i]);","width":140,"height":40,"type":"Блок","isMenuBlock":false,"fontSize":14,"textHeight":14,"isBold":false,"isItalic":false,"textAlign":"center","labelsPosition":1},{"x":860,"y":990,"text":"вывод summ","width":120,"height":40,"type":"Ввод / вывод","isMenuBlock":false,"fontSize":14,"textHeight":14,"isBold":false,"isItalic":false,"textAlign":"center","labelsPosition":1},{"x":1130,"y":990,"text":"В массиве нет отрицательныйх элементов массива","width":360,"height":40,"type":"Ввод / вывод","isMenuBlock":false,"fontSize":14,"textHeight":14,"isBold":false,"isItalic":false,"textAlign":"center","labelsPosition":1},{"x":930,"y":940,"text":"!negative","width":100,"height":40,"type":"Условие","isMenuBlock":false,"fontSize":14,"textHeight":14,"isBold":false,"isItalic":false,"textAlign":"center","labelsPosition":2},{"x":1080,"y":1130,"text":"ввод a","width":120,"height":40,"type":"Ввод / вывод","isMenuBlock":false,"fontSize":14,"textHeight":14,"isBold":false,"isItalic":false,"textAlign":"center","labelsPosition":1},{"x":1080,"y":1190,"text":"ввод b","width":120,"height":40,"type":"Ввод / вывод","isMenuBlock":false,"fontSize":14,"textHeight":14,"isBold":false,"isItalic":false,"textAlign":"center","labelsPosition":1},{"x":1080,"y":1250,"text":"a > b","width":100,"height":40,"type":"Условие","isMenuBlock":false,"fontSize":14,"textHeight":14,"isBold":false,"isItalic":false,"textAlign":"center","labelsPosition":1},{"x":1150,"y":1310,"text":"k = a;\r\na = b;\r\nb = k;","width":100,"height":60,"type":"Блок","isMenuBlock":false,"fontSize":14,"textHeight":14,"isBold":false,"isItalic":false,"textAlign":"left","labelsPosition":1},{"x":1150,"y":1400,"text":"a == b","width":100,"height":40,"type":"Условие","isMenuBlock":false,"fontSize":14,"textHeight":14,"isBold":false,"isItalic":false,"textAlign":"center","labelsPosition":1},{"x":1320,"y":1450,"text":"A и B не могут быть одинаковыми.","width":240,"height":40,"type":"Ввод / вывод","isMenuBlock":false,"fontSize":14,"textHeight":14,"isBold":false,"isItalic":false,"textAlign":"center","labelsPosition":1},{"x":1070,"y":1450,"text":"break;","width":100,"height":40,"type":"Блок","isMenuBlock":false,"fontSize":14,"textHeight":14,"isBold":false,"isItalic":false,"textAlign":"center","labelsPosition":1},{"x":1000,"y":1090,"text":"true","width":100,"height":40,"type":"Условие","isMenuBlock":false,"fontSize":14,"textHeight":14,"isBold":false,"isItalic":false,"textAlign":"center","labelsPosition":1},{"x":900,"y":1620,"text":"!((arr[i] >= a) && (arr[i] <= b))","width":200,"height":60,"type":"Условие","isMenuBlock":false,"fontSize":14,"textHeight":14,"isBold":false,"isItalic":false,"textAlign":"center","labelsPosition":1},{"x":1060,"y":1670,"text":"new_arr[j++] = arr[i];","width":140,"height":40,"type":"Блок","isMenuBlock":false,"fontSize":14,"textHeight":14,"isBold":false,"isItalic":false,"textAlign":"center","labelsPosition":1},{"x":900,"y":1540,"text":"i от 0 до size","width":100,"height":40,"type":"Цикл for","isMenuBlock":false,"fontSize":14,"textHeight":14,"isBold":false,"isItalic":false,"textAlign":"center","labelsPosition":1},{"x":900,"y":1820,"text":"new_arr[i] = 0;","width":100,"height":40,"type":"Блок","isMenuBlock":false,"fontSize":14,"textHeight":14,"isBold":false,"isItalic":false,"textAlign":"center","labelsPosition":1},{"x":900,"y":1760,"text":"i от j до size","width":100,"height":40,"type":"Цикл for","isMenuBlock":false,"fontSize":14,"textHeight":14,"isBold":false,"isItalic":false,"textAlign":"center","labelsPosition":1},{"x":1050,"y":1820,"text":"draw_float_array","width":140,"height":40,"type":"Подпрограмма","isMenuBlock":false,"fontSize":14,"textHeight":14,"isBold":false,"isItalic":false,"textAlign":"center","labelsPosition":1},{"x":1050,"y":1880,"text":"конец","width":100,"height":30,"type":"Начало / конец","isMenuBlock":false,"fontSize":14,"textHeight":14,"isBold":false,"isItalic":false,"textAlign":"center","labelsPosition":1}],"arrows":[{"startIndex":0,"endIndex":5,"startConnectorIndex":2,"endConnectorIndex":0,"nodes":[{"x":600,"y":275},{"x":600,"y":280},{"x":600,"y":300}],"counts":[1,1,1]},{"startIndex":2,"endIndex":3,"startConnectorIndex":3,"endConnectorIndex":3,"nodes":[{"x":750,"y":420},{"x":620,"y":420},{"x":620,"y":480},{"x":640,"y":480}],"counts":[1,1,1,1]},{"startIndex":2,"endIndex":4,"startConnectorIndex":1,"endConnectorIndex":0,"nodes":[{"x":850,"y":420},{"x":1170,"y":420},{"x":1170,"y":440},{"x":1170,"y":460}],"counts":[1,1,1,1]},{"startIndex":1,"endIndex":2,"startConnectorIndex":2,"endConnectorIndex":0,"nodes":[{"x":800,"y":380},{"x":800,"y":380},{"x":800,"y":400}],"counts":[1,1,1]},{"startIndex":5,"endIndex":1,"startConnectorIndex":1,"endConnectorIndex":0,"nodes":[{"x":650,"y":320},{"x":800,"y":320},{"x":800,"y":340}],"counts":[1,1,1]},{"startIndex":3,"endIndex":5,"startConnectorIndex":2,"endConnectorIndex":2,"nodes":[{"x":860,"y":500},{"x":860,"y":520},{"x":600,"y":520},{"x":600,"y":360},{"x":600,"y":340}],"counts":[1,1,1,1,1]},{"startIndex":4,"endIndex":5,"startConnectorIndex":2,"endConnectorIndex":2,"nodes":[{"x":1170,"y":500},{"x":1170,"y":520},{"x":600,"y":520},{"x":600,"y":360},{"x":600,"y":340}],"counts":[1,1,1,1,1]},{"startIndex":5,"endIndex":7,"startConnectorIndex":3,"endConnectorIndex":0,"nodes":[{"x":550,"y":320},{"x":530,"y":320},{"x":530,"y":550},{"x":600,"y":550},{"x":600,"y":570}],"counts":[1,1,1,1,1]},{"startIndex":7,"endIndex":6,"startConnectorIndex":2,"endConnectorIndex":0,"nodes":[{"x":600,"y":610},{"x":600,"y":610},{"x":600,"y":630}],"counts":[1,1,1]},{"startIndex":6,"endIndex":7,"startConnectorIndex":2,"endConnectorIndex":3,"nodes":[{"x":600,"y":670},{"x":600,"y":690},{"x":510,"y":690},{"x":510,"y":590},{"x":530,"y":590},{"x":550,"y":590}],"counts":[1,1,1,1,1,1]},{"startIndex":7,"endIndex":8,"startConnectorIndex":1,"endConnectorIndex":0,"nodes":[{"x":650,"y":590},{"x":690,"y":590},{"x":690,"y":710},{"x":600,"y":710},{"x":600,"y":730}],"counts":[1,1,1,1,1]},{"startIndex":8,"endIndex":9,"startConnectorIndex":2,"endConnectorIndex":0,"nodes":[{"x":600,"y":770},{"x":600,"y":770},{"x":600,"y":790}],"counts":[1,1,1]},{"startIndex":9,"endIndex":13,"startConnectorIndex":2,"endConnectorIndex":0,"nodes":[{"x":600,"y":830},{"x":600,"y":830},{"x":600,"y":850}],"counts":[1,1,1]},{"startIndex":13,"endIndex":10,"startConnectorIndex":2,"endConnectorIndex":0,"nodes":[{"x":600,"y":890},{"x":600,"y":890},{"x":600,"y":910}],"counts":[1,1,1]},{"startIndex":10,"endIndex":11,"startConnectorIndex":3,"endConnectorIndex":0,"nodes":[{"x":510,"y":940},{"x":480,"y":940},{"x":480,"y":960},{"x":480,"y":980}],"counts":[1,1,1,1]},{"startIndex":10,"endIndex":12,"startConnectorIndex":1,"endConnectorIndex":0,"nodes":[{"x":690,"y":940},{"x":710,"y":940},{"x":710,"y":1000},{"x":710,"y":1020}],"counts":[1,1,1,1]},{"startIndex":12,"endIndex":14,"startConnectorIndex":1,"endConnectorIndex":0,"nodes":[{"x":760,"y":1040},{"x":800,"y":1040},{"x":800,"y":1050},{"x":800,"y":1070}],"counts":[1,1,1,1]},{"startIndex":11,"endIndex":13,"startConnectorIndex":2,"endConnectorIndex":3,"nodes":[{"x":480,"y":1020},{"x":480,"y":1040},{"x":410,"y":1040},{"x":410,"y":870},{"x":530,"y":870},{"x":550,"y":870}],"counts":[1,1,1,1,1,1]},{"startIndex":12,"endIndex":13,"startConnectorIndex":3,"endConnectorIndex":3,"nodes":[{"x":660,"y":1040},{"x":410,"y":1040},{"x":410,"y":870},{"x":530,"y":870},{"x":550,"y":870}],"counts":[1,1,1,1,1]},{"startIndex":14,"endIndex":13,"startConnectorIndex":2,"endConnectorIndex":3,"nodes":[{"x":800,"y":1110},{"x":800,"y":1130},{"x":410,"y":1130},{"x":410,"y":870},{"x":530,"y":870},{"x":550,"y":870}],"counts":[1,1,1,1,1,1]},{"startIndex":13,"endIndex":17,"startConnectorIndex":1,"endConnectorIndex":0,"nodes":[{"x":650,"y":870},{"x":930,"y":870},{"x":930,"y":900},{"x":930,"y":920}],"counts":[1,1,1,1]},{"startIndex":17,"endIndex":15,"startConnectorIndex":3,"endConnectorIndex":0,"nodes":[{"x":880,"y":940},{"x":860,"y":940},{"x":860,"y":950},{"x":860,"y":970}],"counts":[1,1,1,1]},{"startIndex":17,"endIndex":16,"startConnectorIndex":1,"endConnectorIndex":0,"nodes":[{"x":980,"y":940},{"x":1130,"y":940},{"x":1130,"y":950},{"x":1130,"y":970}],"counts":[1,1,1,1]},{"startIndex":15,"endIndex":25,"startConnectorIndex":2,"endConnectorIndex":0,"nodes":[{"x":860,"y":1010},{"x":860,"y":1050},{"x":1000,"y":1050},{"x":1000,"y":1070}],"counts":[1,1,1,1]},{"startIndex":16,"endIndex":25,"startConnectorIndex":2,"endConnectorIndex":0,"nodes":[{"x":1130,"y":1010},{"x":1130,"y":1050},{"x":1000,"y":1050},{"x":1000,"y":1070}],"counts":[1,1,1,1]},{"startIndex":25,"endIndex":18,"startConnectorIndex":1,"endConnectorIndex":0,"nodes":[{"x":1050,"y":1090},{"x":1080,"y":1090},{"x":1080,"y":1110}],"counts":[1,1,1]},{"startIndex":18,"endIndex":19,"startConnectorIndex":2,"endConnectorIndex":0,"nodes":[{"x":1080,"y":1150},{"x":1080,"y":1150},{"x":1080,"y":1170}],"counts":[1,1,1]},{"startIndex":19,"endIndex":20,"startConnectorIndex":2,"endConnectorIndex":0,"nodes":[{"x":1080,"y":1210},{"x":1080,"y":1210},{"x":1080,"y":1230}],"counts":[1,1,1]},{"startIndex":20,"endIndex":21,"startConnectorIndex":1,"endConnectorIndex":0,"nodes":[{"x":1130,"y":1250},{"x":1150,"y":1250},{"x":1150,"y":1260},{"x":1150,"y":1280}],"counts":[1,1,1,1]},{"startIndex":20,"endIndex":22,"startConnectorIndex":3,"endConnectorIndex":0,"nodes":[{"x":1030,"y":1250},{"x":1010,"y":1250},{"x":1010,"y":1360},{"x":1150,"y":1360},{"x":1150,"y":1380}],"counts":[1,1,1,1,1]},{"startIndex":21,"endIndex":22,"startConnectorIndex":2,"endConnectorIndex":0,"nodes":[{"x":1150,"y":1340},{"x":1150,"y":1360},{"x":1150,"y":1380}],"counts":[1,1,1]},{"startIndex":22,"endIndex":23,"startConnectorIndex":1,"endConnectorIndex":0,"nodes":[{"x":1200,"y":1400},{"x":1320,"y":1400},{"x":1320,"y":1410},{"x":1320,"y":1430}],"counts":[1,1,1,1]},{"startIndex":22,"endIndex":24,"startConnectorIndex":3,"endConnectorIndex":0,"nodes":[{"x":1100,"y":1400},{"x":1070,"y":1400},{"x":1070,"y":1410},{"x":1070,"y":1430}],"counts":[1,1,1,1]},{"startIndex":23,"endIndex":25,"startConnectorIndex":2,"endConnectorIndex":2,"nodes":[{"x":1320,"y":1470},{"x":1320,"y":1490},{"x":1000,"y":1490},{"x":1000,"y":1130},{"x":1000,"y":1110}],"counts":[1,1,1,1,1]},{"startIndex":24,"endIndex":25,"startConnectorIndex":2,"endConnectorIndex":2,"nodes":[{"x":1070,"y":1470},{"x":1070,"y":1490},{"x":1000,"y":1490},{"x":1000,"y":1130},{"x":1000,"y":1110}],"counts":[1,1,1,1,1]},{"startIndex":25,"endIndex":28,"startConnectorIndex":3,"endConnectorIndex":0,"nodes":[{"x":950,"y":1090},{"x":900,"y":1090},{"x":900,"y":1500},{"x":900,"y":1520}],"counts":[1,1,1,1]},{"startIndex":28,"endIndex":26,"startConnectorIndex":2,"endConnectorIndex":0,"nodes":[{"x":900,"y":1560},{"x":900,"y":1570},{"x":900,"y":1590}],"counts":[1,1,1]},{"startIndex":26,"endIndex":27,"startConnectorIndex":1,"endConnectorIndex":0,"nodes":[{"x":1000,"y":1620},{"x":1060,"y":1620},{"x":1060,"y":1630},{"x":1060,"y":1650}],"counts":[1,1,1,1]},{"startIndex":26,"endIndex":28,"startConnectorIndex":3,"endConnectorIndex":3,"nodes":[{"x":800,"y":1620},{"x":780,"y":1620},{"x":780,"y":1540},{"x":830,"y":1540},{"x":850,"y":1540}],"counts":[1,1,1,1,1]},{"startIndex":27,"endIndex":28,"startConnectorIndex":2,"endConnectorIndex":3,"nodes":[{"x":1060,"y":1690},{"x":1060,"y":1710},{"x":780,"y":1710},{"x":780,"y":1540},{"x":830,"y":1540},{"x":850,"y":1540}],"counts":[1,1,1,1,1,1]},{"startIndex":28,"endIndex":30,"startConnectorIndex":1,"endConnectorIndex":0,"nodes":[{"x":950,"y":1540},{"x":1140,"y":1540},{"x":1140,"y":1720},{"x":900,"y":1720},{"x":900,"y":1740}],"counts":[1,1,1,1,1]},{"startIndex":30,"endIndex":29,"startConnectorIndex":2,"endConnectorIndex":0,"nodes":[{"x":900,"y":1780},{"x":900,"y":1780},{"x":900,"y":1800}],"counts":[1,1,1]},{"startIndex":29,"endIndex":30,"startConnectorIndex":2,"endConnectorIndex":3,"nodes":[{"x":900,"y":1840},{"x":900,"y":1860},{"x":830,"y":1860},{"x":830,"y":1760},{"x":850,"y":1760}],"counts":[1,1,1,1,1]},{"startIndex":30,"endIndex":31,"startConnectorIndex":1,"endConnectorIndex":0,"nodes":[{"x":950,"y":1760},{"x":1050,"y":1760},{"x":1050,"y":1780},{"x":1050,"y":1800}],"counts":[1,1,1,1]},{"startIndex":31,"endIndex":32,"startConnectorIndex":2,"endConnectorIndex":0,"nodes":[{"x":1050,"y":1840},{"x":1050,"y":1850},{"x":1050,"y":1865}],"counts":[1,1,1]}],"x0":500.09405967565743,"y0":-69.62188878896552}